fastpdf4llm/__init__.py
fastpdf4llm/convert/__init__.py
fastpdf4llm/convert/doc.py
fastpdf4llm/convert/page.py
fastpdf4llm/models/__init__.py
fastpdf4llm/models/constants.py
fastpdf4llm/models/content.py
fastpdf4llm/models/line.py
fastpdf4llm/models/paragraph.py
fastpdf4llm/models/parse_options.py
fastpdf4llm/models/progress.py
fastpdf4llm/utils/__init__.py
fastpdf4llm/utils/font.py
fastpdf4llm/utils/number_utils.py
fastpdf4llm/utils/table_utils.py
fastpdf4llm-0.1.5.dist-info/METADATA
fastpdf4llm-0.1.5.dist-info/WHEEL
fastpdf4llm-0.1.5.dist-info/licenses/LICENSE
fastpdf4llm-0.1.5.dist-info/RECORD
