Metadata-Version: 2.4
Name: fastpdf4llm
Version: 0.1.5
Summary: A fast PDF to Markdown converter optimized for LLM processing
License: MIT
License-File: LICENSE
Keywords: pdf,markdown,llm,converter,pdfplumber
Author: Yue Fei
Author-email: feiyue297@qq.com
Requires-Python: >=3.9,<4.0
Classifier: Development Status :: 3 - Alpha
Classifier: Intended Audience :: Developers
Classifier: License :: OSI Approved :: MIT License
Classifier: Programming Language :: Python :: 3
Classifier: Programming Language :: Python :: 3.9
Classifier: Programming Language :: Python :: 3.10
Classifier: Programming Language :: Python :: 3.11
Classifier: Programming Language :: Python :: 3.12
Classifier: Programming Language :: Python :: 3.13
Classifier: Programming Language :: Python :: 3.14
Classifier: Programming Language :: Python :: 3.8
Classifier: Topic :: Software Development :: Libraries :: Python Modules
Classifier: Topic :: Text Processing :: Markup
Requires-Dist: loguru (>=0.7.0,<0.8.0)
Requires-Dist: pdfplumber (>=0.11.3)
Requires-Dist: pydantic (>=2.0.0,<3.0.0)
Project-URL: Repository, https://github.com/moria97/fastpdf4llm
